pygamefwk/__init__.py
pygamefwk/error.py
pygamefwk/event.py
pygamefwk/game.py
pygamefwk/input.py
pygamefwk/instantiate.py
pygamefwk/location.py
pygamefwk/manger.py
pygamefwk/mouse.py
pygamefwk/scene.py
pygamefwk/sheet.py
pygamefwk/timertask.py
pygamefwk/util.py
pygamefwk/objects/__init__.py
pygamefwk/objects/camera.py
pygamefwk/objects/component.py
pygamefwk/objects/gameobject.py
pygamefwk/objects/mapobject.py
pygamefwk/objects/object.py
pygamefwk/objects/parent.py
pygamefwk/objects/tilemap.py
pygamefwk/objects/components/__init__.py
pygamefwk/objects/components/animation.py
pygamefwk/objects/components/animationManager.py
pygamefwk/objects/components/collide_mouse.py
pygamefwk/objects/components/image.py
pygamefwk/objects/components/physics.py
pygamefwk/objects/components/reset.py
pygamefwk/objects/components/soundListener.py
pygamefwk/objects/components/soundSource.py
pygamefwk/objects/ui/__init__.py
pygamefwk/objects/ui/button.py
pygamefwk/objects/ui/inputfield.py
pygamefwk/objects/ui/text.py
pygamefwk/objects/ui/ui.py
pygamefwk-1.1.0.dist-info/licenses/LICENSE
pygamefwk-1.1.0.dist-info/METADATA
pygamefwk-1.1.0.dist-info/WHEEL
pygamefwk-1.1.0.dist-info/top_level.txt
pygamefwk-1.1.0.dist-info/RECORD
