Metadata-Version: 2.4
Name: pygamefwk
Version: 1.1.0
Summary: pygame framework
Home-page: https://github.com/fireing123/pygamefwk
Author: fireing123
Author-email: gimd82368@gmail.com
Keywords: pygame framework,fireing123,pygame
License-File: LICENSE
Requires-Dist: pygame
Dynamic: author
Dynamic: author-email
Dynamic: description
Dynamic: description-content-type
Dynamic: home-page
Dynamic: keywords
Dynamic: license-file
Dynamic: requires-dist
Dynamic: summary
